microshard_uuid/__init__.py
microshard_uuid/core.py
microshard_uuid/py.typed
microshard_uuid-1.0.0.dist-info/licenses/LICENSE
microshard_uuid-1.0.0.dist-info/METADATA
microshard_uuid-1.0.0.dist-info/WHEEL
microshard_uuid-1.0.0.dist-info/top_level.txt
microshard_uuid-1.0.0.dist-info/RECORD
