Metadata-Version: 2.4
Name: microshard-uuid
Version: 1.0.0
Summary: A zero-lookup, partition-aware UUIDv8 implementation with microsecond precision.
Author: dilipvamsi
License-Expression: MIT
Project-URL: Homepage, https://github.com/dilipvamsi/microshard-uuid
Project-URL: Bug Tracker, https://github.com/dilipvamsi/microshard-uuid/issues
Project-URL: Documentation, https://github.com/dilipvamsi/microshard-uuid#readme
Keywords: uuid,uuidv8,sharding,distributed-systems,database,partitioning,microshard
Classifier: Development Status :: 5 - Production/Stable
Classifier: Intended Audience :: Developers
Classifier: Operating System :: OS Independent
Classifier: Programming Language :: Python :: 3
Classifier: Programming Language :: Python :: 3.7
Classifier: Programming Language :: Python :: 3.8
Classifier: Programming Language :: Python :: 3.9
Classifier: Programming Language :: Python :: 3.10
Classifier: Programming Language :: Python :: 3.11
Classifier: Programming Language :: Python :: 3.12
Classifier: Programming Language :: Python :: 3.13
Classifier: Topic :: Database
Classifier: Topic :: Software Development :: Libraries :: Python Modules
Classifier: Typing :: Typed
Requires-Python: >=3.7
License-File: LICENSE
Dynamic: license-file
